setup.py
ASUSCloudInfra/VERSION
ASUSCloudInfra/__init__ .py
ASUSCloudInfra.egg-info/PKG-INFO
ASUSCloudInfra.egg-info/SOURCES.txt
ASUSCloudInfra.egg-info/dependency_links.txt
ASUSCloudInfra.egg-info/not-zip-safe
ASUSCloudInfra.egg-info/requires.txt
ASUSCloudInfra.egg-info/top_level.txt
ASUSCloudInfra/AIMaker/__init__.py
ASUSCloudInfra/AIMaker/update_result.py
ASUSCloudInfra/AIMakerMonitor/__init__.py
ASUSCloudInfra/AIMakerMonitor/prometheus.py
ASUSCloudInfra/Base/__init__.py
ASUSCloudInfra/Base/api_token.py
ASUSCloudInfra/Base/config.py
ASUSCloudInfra/Base/container.py
ASUSCloudInfra/Base/container_service.py
ASUSCloudInfra/Base/docker_image.py
ASUSCloudInfra/Base/enviroment.py
ASUSCloudInfra/Base/flavor.py
ASUSCloudInfra/Base/image_repository.py
ASUSCloudInfra/Base/mount_volume.py
ASUSCloudInfra/Base/network.py
ASUSCloudInfra/Base/project.py
ASUSCloudInfra/Base/sftp_client.py
ASUSCloudInfra/Base/storage.py
ASUSCloudInfra/Base/storage_service.py
ASUSCloudInfra/Base/SFTP/__init__.py
ASUSCloudInfra/Base/SFTP/scp.py
ASUSCloudInfra/Docker/__init__.py
ASUSCloudInfra/Docker/docker.py