Metadata-Version: 1.0
Name: ASUSCloudInfra
Version: 1.1.12
Summary: the library for ASUS Cloud Infra
Home-page: UNKNOWN
Author: scott_su
Author-email: scott_su@asus.com
License: MIT
Platform: UNKNOWN
